setup.py
volcengine-sdk-java-rec-master.zip
module/__init__.py
module/yjl-first-pypi.py
yjl_first_pypi.egg-info/PKG-INFO
yjl_first_pypi.egg-info/SOURCES.txt
yjl_first_pypi.egg-info/dependency_links.txt
yjl_first_pypi.egg-info/top_level.txt