Metadata-Version: 2.1
Name: yjl-first-pypi
Version: 0.0.3
Summary: A successful sign for python setup
Home-page: http://python4office.cn/upload-pip/
Author: yjl-first-pypi
Author-email: yaojiuox@qq.com
License: MIT Licence
Keywords: pip,yjl-first-pypi
Platform: any
